xappt/__init__.py
xappt/__version__.py
xappt/cli.py
xappt/config.py
xappt/constants.py
xappt/managers/__init__.py
xappt/managers/plugin_manager.py
xappt/models/__init__.py
xappt/models/callback.py
xappt/models/mixins/__init__.py
xappt/models/mixins/config.py
xappt/models/parameter/__init__.py
xappt/models/parameter/base.py
xappt/models/parameter/convert.py
xappt/models/parameter/errors.py
xappt/models/parameter/meta.py
xappt/models/parameter/model.py
xappt/models/parameter/parameters.py
xappt/models/parameter/validators.py
xappt/models/plugins/__init__.py
xappt/models/plugins/base.py
xappt/models/plugins/interface.py
xappt/models/plugins/tool.py
xappt/plugins/__init__.py
xappt/plugins/interfaces/__init__.py
xappt/plugins/interfaces/stdio.py
xappt/plugins/interfaces/test.py
xappt/plugins/tools/__init__.py
xappt/plugins/tools/example.py
xappt/plugins/tools/interactive.py
xappt/plugins/tools/examples/__init__.py
xappt/plugins/tools/examples/data_types.py
xappt/plugins/tools/examples/modify_choices.py
xappt/plugins/tools/examples/tool_chaining.py
xappt/utilities/__init__.py
xappt/utilities/command_runner.py
xappt/utilities/find_python.py
xappt/utilities/git_tools.py
xappt/utilities/humanize.py
xappt/utilities/setup_helpers.py
xappt/utilities/termsize.py
xappt/utilities/path/__init__.py
xappt/utilities/path/misc.py
xappt/utilities/path/temp_path.py
xappt-0.9.3.dist-info/LICENSE
xappt-0.9.3.dist-info/METADATA
xappt-0.9.3.dist-info/WHEEL
xappt-0.9.3.dist-info/entry_points.txt
xappt-0.9.3.dist-info/top_level.txt
xappt-0.9.3.dist-info/RECORD
