Metadata-Version: 2.1
Name: xappt
Version: 0.9.3
Summary: eXtensible APPlication Toolkit.
Home-page: https://github.com/cmontesano/xappt
Author: Christopher Montesano
Author-email: cmdev.00+xappt@gmail.com
License: MIT
Platform: any
Classifier: Topic :: Utilities
Classifier: Development Status :: 4 - Beta
Classifier: Intended Audience :: Developers
Classifier: License :: OSI Approved :: MIT License
Classifier: Operating System :: OS Independent
Classifier: Programming Language :: Python :: 3
Classifier: Programming Language :: Python :: 3.7
Classifier: Programming Language :: Python :: 3.8
Classifier: Programming Language :: Python :: 3.9
Requires-Python: >=3.7, <4
License-File: LICENSE
Requires-Dist: colorama (~=0.4.3)
